{"The": {"DET": 29}, "Wonder": {"NOUN": 2}, "Years": {"NOUN": 2}, "What": {"PRON": 9}, "a": {"DET": 61}, "quality": {"NOUN": 1}, "show": {"NOUN": 13, "VERB": 1}, ".": {".": 120}, "I": {"PRON": 62}, "hope": {"VERB": 4}, "it": {"PRON": 51}, "wins": {"VERB": 1}, "an": {"DET": 10}, "Emmy": {"NOUN": 1}, "'m": {"VERB": 6}, "loving": {"VERB": 1}, "the": {"DET": 82}, "!": {".": 25}, "Wife": {"NOUN": 1}, "Swap": {"NOUN": 1}, "episode": {"NOUN": 8}, "ID": {"NOUN": 1}, "There": {"DET": 3}, "\u2019": {"NOUN": 16, "ADJ": 4, "VERB": 14}, "s": {"VERB": 3, "NOUN": 5, "ADJ": 1}, "kid": {"NOUN": 1}, "who": {"PRON": 4}, "smokes": {"VERB": 1}, "weed": {"VERB": 1}, "out": {"ADP": 3, "PRT": 3}, "of": {"ADP": 69}, "apple": {"NOUN": 1}, ",": {".": 89}, "and": {"CONJ": 43}, "believe": {"VERB": 4}, "he": {"PRON": 4}, "has": {"VERB": 4}, "suitcase": {"ADJ": 1}, "full": {"ADJ": 3}, "glue": {"ADJ": 1, "NOUN": 1}, "sticks": {"NOUN": 1}, "for": {"ADP": 22}, "huffing": {"VERB": 1}, "But": {"CONJ": 2}, "might": {"VERB": 1}, "be": {"VERB": 8}, "different": {"ADJ": 2}, "Hi": {"NOUN": 1}, "Hustler": {"NOUN": 1}, "Anyone": {"NOUN": 3}, "see": {"VERB": 3}, "latest": {"ADJ": 1}, "?": {".": 57}, "Kwasi": {"NOUN": 1}, "gives": {"VERB": 1}, "away": {"ADV": 4}, "biggest": {"ADJ": 1}, "clue": {"NOUN": 1}, "in": {"ADP": 28}, "first": {"ADJ": 2}, "minute": {"NOUN": 1}, "when": {"ADV": 2}, "said": {"VERB": 2}, "went": {"VERB": 2}, "to": {"PRT": 56}, "University": {"NOUN": 2}, "Washington": {"NOUN": 2}, "that": {"ADP": 9, "DET": 10, "ADV": 1}, "their.mascot": {"NOUN": 1}, "was": {"VERB": 12}, "Cubs": {"NOUN": 2}, "Its": {"PRON": 4}, "Huskies": {"NOUN": 1}, "He": {"PRON": 2}, "\u201c": {"ADJ": 1, "NOUN": 2}, "WashU.": {"NOUN": 1}, "\u201d": {"NOUN": 3}, "Could": {"NOUN": 1}, "St.": {"NOUN": 1}, "Louis": {"NOUN": 1}, "are": {"VERB": 4}, "Bears": {"NOUN": 1}, "And": {"CONJ": 1}, "isnt": {"NOUN": 1}, "either": {"CONJ": 1, "DET": 1}, "ca": {"VERB": 9}, "n't": {"ADV": 16}, "find": {"VERB": 7}, "``": {".": 36}, "Kids": {"NOUN": 1}, "say": {"VERB": 3}, "darndest": {"ADJ": 1}, "things": {"NOUN": 2}, "''": {".": 36}, "anywhere": {"ADV": 2}, "besides": {"VERB": 1}, "clips": {"NOUN": 1}, "on": {"ADP": 40}, "youtube": {"NOUN": 1}, "'s": {"VERB": 15, "PRT": 10}, "no": {"DET": 10}, "streaming": {"NOUN": 1, "VERB": 1, "ADJ": 1}, "platform": {"NOUN": 1}, "buy": {"VERB": 3}, "episodes": {"NOUN": 5}, "ANYWHERE": {"NOUN": 1}, "like": {"ADP": 7}, "if": {"ADP": 7}, "never": {"ADV": 1}, "existed": {"VERB": 1}, "Can": {"VERB": 2}, "someone": {"NOUN": 8}, "help": {"VERB": 2, "NOUN": 4}, "me": {"PRON": 8}, "If": {"ADP": 2}, "y'all": {"ADV": 1}, "know": {"VERB": 6}, "how": {"ADV": 5}, "can": {"VERB": 10}, "watch": {"VERB": 10}, "let": {"VERB": 1}, "Since": {"ADP": 1}, "there": {"DET": 1, "ADV": 3}, "is": {"VERB": 26}, "Freeform": {"NOUN": 3}, "subreddit": {"NOUN": 3}, "have": {"VERB": 19}, "ask": {"VERB": 1}, "here": {"ADV": 4}, "else": {"ADV": 3}, "having": {"VERB": 1}, "occasional": {"ADJ": 1}, "playback": {"NOUN": 2}, "issues": {"NOUN": 1}, "while": {"ADP": 5}, "video": {"NOUN": 3}, "am": {"VERB": 3}, "trying": {"VERB": 2}, "keeps": {"NOUN": 1}, "getting": {"VERB": 6}, "sync": {"NOUN": 1}, "with": {"ADP": 5}, "audio": {"NOUN": 2, "ADJ": 1}, "or": {"CONJ": 12}, "goes": {"VERB": 1}, "back": {"PRT": 1, "ADV": 4}, "second": {"ADJ": 2}, "every": {"DET": 3}, "4": {"NUM": 1}, "seconds": {"NOUN": 1}, "EXTREMELY": {"NOUN": 1}, "FRUSTRATING": {"NOUN": 1}, "refreshed": {"VERB": 1}, "page": {"NOUN": 1}, "10": {"NUM": 2}, "times": {"NOUN": 3}, "paused": {"VERB": 1}, "dozens": {"NOUN": 1}, "gone": {"VERB": 2}, "few": {"ADJ": 2}, "wo": {"VERB": 1}, "FIX": {"VERB": 1}, "really": {"ADV": 8}, "wan": {"VERB": 1}, "na": {"PRT": 1}, "break": {"VERB": 2, "NOUN": 1}, "right": {"ADV": 1, "NOUN": 2}, "now": {"ADV": 6}, "this": {"DET": 20}, "website": {"NOUN": 2}, "freeform.com": {"NOUN": 1}, "actual": {"ADJ": 2}, "shit": {"NOUN": 1, "VERB": 1}, "A": {"NOUN": 4, "DET": 5}, "good": {"ADJ": 3}, "shows": {"NOUN": 3, "VERB": 1}, "ads": {"NOUN": 4}, "but": {"CONJ": 13}, "holy": {"VERB": 1}, "IS": {"NOUN": 1}, "WHACK": {"NOUN": 1}, "Any": {"DET": 1}, "one": {"NUM": 6, "NOUN": 2}, "fix": {"VERB": 1}, "Also": {"ADV": 1}, "why": {"ADV": 4}, "sub": {"NOUN": 2, "ADJ": 1}, "so": {"ADV": 6}, "small": {"ADJ": 2}, "Seems": {"VERB": 1}, "bit": {"NOUN": 1}, "such": {"DET": 1}, "big": {"ADJ": 2}, "company": {"NOUN": 1}, "It": {"PRON": 11}, "not": {"ADV": 13}, "official": {"ADJ": 2}, "promoted": {"VERB": 1}, "Plus": {"CONJ": 1}, "often": {"ADV": 2}, "gets": {"VERB": 4}, "spam": {"NOUN": 1}, "...": {".": 2}, "Many": {"ADJ": 1}, "non": {"VERB": 1}, "subs": {"NOUN": 1}, "get": {"VERB": 9}, "plenty": {"NOUN": 1}, "followers": {"NOUN": 1}, "True": {"NOUN": 1}, "still": {"ADV": 4}, "-": {".": 66}, "other": {"ADJ": 4}, "reasons": {"NOUN": 1}, "gave": {"VERB": 1}, "hub": {"NOUN": 1}, "since": {"ADP": 3}, "about": {"ADP": 7}, "TV": {"NOUN": 5}, "network": {"NOUN": 2}, "rather": {"ADV": 2}, "than": {"ADP": 2}, "specific": {"ADJ": 2}, "show/franchise": {"NOUN": 1}, "generally": {"ADV": 1}, "does": {"VERB": 5}, "much": {"ADJ": 3, "ADV": 1}, "interest": {"NOUN": 1}, "Not": {"ADV": 1}, "many": {"ADJ": 1}, "people": {"NOUN": 1}, "ABC": {"NOUN": 45}, "general": {"ADJ": 1}, "they": {"PRON": 11}, "like/dislike": {"VERB": 1}, "thought": {"VERB": 1}, "would": {"VERB": 5}, "cool": {"ADJ": 1}, "spot": {"NOUN": 1}, "discuss": {"VERB": 1}, "upcoming": {"ADJ": 1}, "current": {"ADJ": 1}, "Like": {"ADP": 1}, "do": {"VERB": 7}, "r/HBOMAX": {"NOUN": 1}, "r/Hulu": {"NOUN": 1}, "r/Netflix": {"NOUN": 1}, "r/TVPlus": {"NOUN": 1}, "etc": {"X": 1}, "then": {"ADV": 5}, "again": {"ADV": 2}, "service": {"NOUN": 1}, "World": {"NOUN": 2}, "News": {"NOUN": 4}, "Tonight": {"NOUN": 1}, "annoyed": {"VERB": 1}, "by": {"ADP": 7}, "lengthy": {"ADJ": 1}, "commercials": {"NOUN": 2}, "fact": {"NOUN": 1}, "David": {"NOUN": 1}, "doesn": {"NOUN": 1}, "t": {"VERB": 2, "NOUN": 5, "ADJ": 4}, "even": {"ADV": 2}, "until": {"ADP": 1}, "3:45": {"NUM": 1}, "minutes": {"NOUN": 4}, "don": {"VERB": 2}, "understand": {"NOUN": 1, "VERB": 1}, "what": {"PRON": 5}, "happens": {"VERB": 2}, "maybe": {"ADV": 1}, "20": {"NUM": 1}, "teases": {"VERB": 1}, "story": {"NOUN": 3}, "go": {"VERB": 3}, "ONE": {"NUM": 1}, "(": {".": 42}, "usually": {"ADV": 1}, "teaser": {"NOUN": 1}, ")": {".": 43}, "another": {"DET": 1}, "commercial": {"ADJ": 2}, "may": {"VERB": 1}, "make": {"VERB": 2}, "sense": {"NOUN": 1}, "terms": {"NOUN": 1}, "advert": {"ADJ": 1}, "dollars": {"NOUN": 1}, "ruins": {"VERB": 1}, "continuity": {"NOUN": 1}, "Unwanted": {"NOUN": 1}, "Narration": {"NOUN": 1}, "Is": {"VERB": 7}, "anyone": {"NOUN": 4}, "unwanted": {"ADJ": 1}, "narration": {"NOUN": 1}, "happened": {"VERB": 2}, "multiple": {"ADJ": 1}, "only": {"ADV": 3, "ADJ": 1}, "channel": {"NOUN": 1}, "We": {"PRON": 2}, "ve": {"ADJ": 1}, "through": {"ADP": 1}, "all": {"DET": 3}, "closed": {"ADJ": 1}, "captioning": {"NOUN": 1}, "guides": {"NOUN": 1}, "re": {"VERB": 1, "ADJ": 1}, "off": {"NOUN": 1, "PRT": 1, "ADP": 1}, "Hellllp": {"VERB": 1}, "Where": {"ADV": 1}, "you": {"PRON": 13}, "old": {"ADJ": 3}, "20/20": {"NUM": 3}, "from": {"ADP": 16}, "1990": {"NUM": 1}, "Anybody": {"NOUN": 1}, "any": {"DET": 5}, "thoughts": {"NOUN": 2}, "Specifically": {"ADV": 1}, "looking": {"VERB": 1}, "1999": {"NUM": 1}, "Walt": {"NOUN": 1}, "Disney": {"NOUN": 8}, "Imagineering": {"NOUN": 1}, "Team": {"NOUN": 1}, "Up": {"NOUN": 2}, "New": {"NOUN": 8}, "Interactive": {"NOUN": 1}, "Series": {"NOUN": 3}, "'Imagine": {"PRT": 1}, "Home": {"NOUN": 2}, "'": {"PRT": 4, ".": 4}, "Why": {"ADV": 1}, "GMA": {"NOUN": 3}, "starts": {"VERB": 4}, "at": {"ADP": 11}, "8am": {"NUM": 2}, "WABC": {"NOUN": 5}, "NYC": {"NOUN": 1}, "saturday": {"NOUN": 2}, "east": {"ADJ": 2}, "coast": {"NOUN": 2}, "markets": {"NOUN": 1}, "7am": {"NUM": 2}, "Kinda": {"NOUN": 1}, "weird": {"VERB": 1}, "flagship": {"NOUN": 1}, "station": {"NOUN": 5}, "7": {"NUM": 3}, "hour": {"NOUN": 1}, "behind": {"ADP": 1}, "compared": {"VERB": 1}, "affiliate": {"NOUN": 1}, "stations": {"NOUN": 1}, "some": {"DET": 4}, "affiliates": {"NOUN": 1}, "Alex": {"NOUN": 3}, "Peterson": {"NOUN": 1}, "ABC27": {"NOUN": 1}, "harassed": {"VERB": 1}, "John": {"NOUN": 2}, "Weaver": {"NOUN": 2}, "founder": {"NOUN": 1}, "Lincoln": {"NOUN": 2}, "Project": {"NOUN": 2}, "longtime": {"ADJ": 1}, "political": {"ADJ": 1}, "operative": {"NOUN": 1}, "co-founder": {"NOUN": 1}, "made": {"VERB": 3}, "sexual": {"ADJ": 2}, "overtures": {"NOUN": 1}, "young": {"ADJ": 1}, "men": {"NOUN": 1}, "sometimes": {"ADV": 1}, "offering": {"VERB": 1}, "them": {"PRON": 5}, "work": {"NOUN": 1}, "politics": {"NOUN": 1}, "scam": {"NOUN": 1}, "videos": {"NOUN": 1}, "been": {"VERB": 5}, "very": {"ADV": 2}, "active": {"ADJ": 1}, "Reddit": {"NOUN": 1}, "last": {"ADJ": 2}, "year": {"NOUN": 2}, "two": {"NUM": 1}, "spammed": {"VERB": 1}, "because": {"ADP": 2}, "its": {"PRON": 4}, "basic": {"ADJ": 1}, "title": {"NOUN": 1}, "cleaning": {"VERB": 1}, "up": {"PRT": 3, "ADV": 1}, "Soaring": {"VERB": 1}, "Double": {"NOUN": 1}, "Digits": {"NOUN": 1}, "Week": {"NOUN": 3}, "Ranks": {"NOUN": 2}, "as": {"ADP": 6}, "No": {"NOUN": 2}, "1": {"NUM": 4}, "Entertainment": {"NOUN": 1}, "Broadcast": {"NOUN": 1}, "Network": {"NOUN": 1}, "Adults": {"NOUN": 1}, "18-49": {"ADJ": 1}, "Sets": {"NOUN": 1}, "Record": {"NOUN": 1}, "Overuse": {"NOUN": 1}, "Grim": {"NOUN": 1}, "Milestone": {"NOUN": 1}, "love": {"VERB": 2}, "Thesaurus": {"NOUN": 1}, "guys": {"NOUN": 1}, "news": {"NOUN": 6}, "anchor": {"NOUN": 1}, "uses": {"VERB": 1}, "phrase": {"NOUN": 1}, "just": {"ADV": 9}, "day": {"NOUN": 1}, "Don": {"NOUN": 2}, "switch": {"VERB": 1}, "crappy": {"ADJ": 1}, "channels": {"NOUN": 1}, "....": {"VERB": 1}, "\u2018": {"NOUN": 1, "VERB": 4, "ADJ": 2, "ADP": 2}, "Live": {"VERB": 1}, "Kelly": {"NOUN": 1}, "Ryan": {"NOUN": 1}, "Builds": {"NOUN": 1}, "6-Week": {"ADJ": 1}, "High": {"NOUN": 2}, "Total": {"NOUN": 2}, "Viewers": {"NOUN": 3}, "Season": {"NOUN": 9}, "Date": {"NOUN": 1}, "View": {"NOUN": 1}, "Households": {"NOUN": 1}, "First": {"ADJ": 1}, "Time": {"NOUN": 1}, "24-Year": {"ADJ": 1}, "History": {"NOUN": 1}, "Sees": {"NOUN": 1}, "Gains": {"NOUN": 1}, "Delivering": {"VERB": 1}, "Most-Watched": {"NOUN": 1}, "6": {"NUM": 1}, "Tamron": {"NOUN": 1}, "Hall": {"NOUN": 1}, "Grows": {"NOUN": 1}, "2nd": {"NUM": 1}, "Straight": {"NOUN": 1}, "6-Month": {"ADJ": 1}, "Announces": {"VERB": 2}, "Early": {"ADJ": 2}, "2021": {"NUM": 2}, "Unscripted": {"NOUN": 2}, "Premiere": {"NOUN": 4}, "Dates": {"NOUN": 2}, "best": {"ADJ": 2}, "programme": {"NOUN": 1}, "done": {"VERB": 2}, "want": {"VERB": 4}, "heck": {"NOUN": 1}, "going": {"VERB": 2}, "Tyra": {"NOUN": 1}, "ruining": {"VERB": 3}, "DWTS": {"NOUN": 1}, "Claire": {"NOUN": 1}, "Dale": {"NOUN": 1}, "Bachelorette": {"NOUN": 1}, "writers": {"NOUN": 1}, "season": {"NOUN": 4}, "finale": {"NOUN": 1}, "Good": {"NOUN": 1}, "Doctor": {"NOUN": 1}, "together": {"ADV": 1}, "Community": {"NOUN": 1}, "fans": {"NOUN": 2}, "Con": {"NOUN": 1}, "MAKE": {"VERB": 1}, "PLAN": {"NOUN": 1}, "TO": {"NOUN": 1}, "VOTE": {"NOUN": 1}, "Broadway": {"NOUN": 2}, "PSA": {"NOUN": 1}, "feat": {"NOUN": 2}, "NY1": {"NOUN": 1}, "NEWS": {"NOUN": 1}, "Deborah": {"NOUN": 1}, "Grausman": {"NOUN": 1}, "voice": {"NOUN": 1}, "Smartie": {"NOUN": 1}, "Sesame": {"NOUN": 1}, "Street": {"NOUN": 2}, "performers": {"NOUN": 1}, "Nat": {"NOUN": 1}, "l": {"VERB": 1}, "Tour": {"NOUN": 1}, "productions": {"NOUN": 1}, "Hamilton": {"NOUN": 1}, "Phantom": {"NOUN": 1}, "Opera": {"NOUN": 1}, "Prom": {"NOUN": 1}, "Fiddler": {"NOUN": 1}, "Roof": {"NOUN": 1}, "Les": {"NOUN": 1}, "Miserables": {"NOUN": 1}, "42nd": {"NUM": 1}, "West": {"NOUN": 1}, "Side": {"NOUN": 1}, "Story": {"NOUN": 1}, "Anything": {"NOUN": 1}, "Goes": {"NOUN": 1}, "Rudolph": {"VERB": 1, "NOUN": 1}, "Red-Nosed": {"ADJ": 2}, "Reindeer": {"NOUN": 2}, "begin": {"VERB": 2}, "airing": {"VERB": 2}, "2020": {"NUM": 7}, "true": {"ADJ": 1}, "will": {"VERB": 3}, "after": {"ADP": 2}, "47": {"NUM": 1}, "years": {"NOUN": 3}, "CBS": {"NOUN": 1}, "Someone": {"NOUN": 1}, "posted": {"VERB": 1}, "Wikipedia": {"NOUN": 1}, "move": {"NOUN": 1}, "Same": {"NOUN": 1, "VERB": 1}, "Frosty/Frosty": {"NOUN": 1}, "Returns": {"NOUN": 2}, "O": {"NOUN": 1}, "Modern": {"ADJ": 1}, "Family": {"NOUN": 1, "ADV": 1}, "4th": {"NUM": 1}, "Promo": {"NOUN": 3}, "Sara": {"NOUN": 2}, "Ramirez": {"NOUN": 1}, "Comes": {"VERB": 1}, "Out": {"PRT": 1, "ADP": 1}, "As": {"ADP": 2, "ADV": 1}, "Non-Binary": {"ADJ": 1}, "[": {"ADJ": 28, "VERB": 1, "ADV": 1}, "Agents": {"NOUN": 26}, "S.H.I.E.L.D": {"NOUN": 26}, "]": {"ADJ": 1, "NOUN": 29}, "Finale": {"NOUN": 4}, "S07E12-13": {"ADJ": 1}, "End": {"NOUN": 3}, "Hand": {"NOUN": 1}, "/": {"NOUN": 1, "VERB": 1}, "'re": {"VERB": 2}, "Fighting": {"VERB": 1}, "For": {"ADP": 1}, "Discussion": {"NOUN": 28}, "Thread": {"NOUN": 27}, "SPOILERS": {"NOUN": 27}, "S07E11": {"NOUN": 1}, "Brand": {"NOUN": 1}, "Day": {"NOUN": 1}, "S07E10": {"NOUN": 1}, "Stolen": {"NOUN": 1}, "Goldbergs": {"NOUN": 2}, "cast": {"NOUN": 2, "ADJ": 1, "VERB": 1}, "producer": {"NOUN": 1}, "panel": {"NOUN": 1}, "Comic-Con": {"NOUN": 1}, "@": {"NOUN": 1}, "S07E09": {"NOUN": 1}, "Have": {"VERB": 1}, "Always": {"NOUN": 1}, "Been": {"NOUN": 1}, "Elizabeth": {"NOUN": 1}, "Henstridge": {"NOUN": 1}, "plays": {"VERB": 1}, "Jemma": {"NOUN": 1}, "Simmons": {"NOUN": 1}, "doing": {"VERB": 1}, "AMA": {"NOUN": 1}, "/r/SHIELD": {"NOUN": 1}, "Thursday": {"NOUN": 1}, "23rd": {"NUM": 1}, "July": {"NOUN": 1}, "noon": {"NOUN": 1}, "PDT": {"NOUN": 1}, "3": {"NUM": 4}, "pm": {"ADV": 1, "NOUN": 1}, "EDT": {"NOUN": 2}, "comment": {"NOUN": 4}, "hours": {"NOUN": 2}, "8": {"NUM": 1}, "You": {"PRON": 3}, "live": {"ADJ": 4}, "countdown": {"NOUN": 1}, ":": {".": 11}, "https": {"NOUN": 6, "ADJ": 1}, "//countle.com/z3fkUE_BV": {"NOUN": 1}, "--": {".": 1}, "bot": {"NOUN": 1}, "send": {"VERB": 2}, "feedback": {"NOUN": 1}, "please": {"VERB": 2, "NOUN": 1}, "below": {"ADP": 1}, "PM": {"NOUN": 1}, "S07E08": {"NOUN": 1}, "After": {"ADP": 3}, "Before": {"ADP": 1}, "S07E07": {"NOUN": 1}, "Totally": {"NOUN": 1}, "Excellent": {"NOUN": 1}, "Adventures": {"NOUN": 1}, "Mack": {"NOUN": 1}, "D": {"NOUN": 1}, "Hey": {"NOUN": 3, "ADJ": 1}, "franky": {"VERB": 1}, "Neef": {"NOUN": 1}, "van": {"NOUN": 1}, "Freek": {"NOUN": 1}, "S07E06": {"NOUN": 1}, "Adapt": {"NOUN": 1}, "Die": {"NOUN": 1}, "S07E05": {"NOUN": 1}, "Trout": {"NOUN": 1}, "Milk": {"NOUN": 1}, "Military": {"ADJ": 1}, "Hello": {"NOUN": 1}, "friend": {"NOUN": 1}, "were": {"VERB": 2}, "discussing": {"VERB": 1}, "disappearance": {"NOUN": 1}, "missing": {"VERB": 1}, "soldier": {"NOUN": 2}, "Vanessa": {"NOUN": 1}, "Guillen": {"NOUN": 1}, "we": {"PRON": 2}, "remembered": {"VERB": 1}, "abc": {"ADP": 1, "NOUN": 3, "ADJ": 2}, "long": {"ADJ": 1}, "time": {"NOUN": 4}, "ago": {"ADP": 1}, "drama": {"NOUN": 1}, "series": {"NOUN": 1}, "had": {"VERB": 3}, "female": {"ADJ": 1}, "suffered": {"VERB": 1}, "abuse": {"NOUN": 1}, "driving": {"VERB": 2}, "crazy": {"ADJ": 1}, "Does": {"NOUN": 1}, "remember": {"VERB": 1}, "name": {"NOUN": 1}, "m": {"ADV": 3, "VERB": 1}, "remembers": {"VERB": 1}, "By": {"ADP": 2}, "chance": {"NOUN": 1}, "Combat": {"NOUN": 1}, "Hospital": {"NOUN": 1}, "Channel": {"NOUN": 5}, "York": {"NOUN": 2}, "Screws": {"NOUN": 1}, "Bolton": {"NOUN": 2}, "hell": {"NOUN": 2}, "They": {"PRON": 3}, "cut": {"VERB": 1}, "interview": {"NOUN": 1}, "forty": {"NOUN": 1}, "switched": {"VERB": 1}, "Match": {"NOUN": 1}, "Game": {"NOUN": 1}, "S07E04": {"NOUN": 1}, "Past": {"NOUN": 1}, "Abv": {"NOUN": 1}, "Fjakslgic": {"NOUN": 1}, "Yes": {"X": 2}, "S07E03": {"NOUN": 1}, "Alien": {"ADJ": 1}, "Commies": {"NOUN": 1}, "Future": {"NOUN": 1}, "Watching": {"VERB": 1}, "Overseas": {"NOUN": 1}, "way": {"NOUN": 3}, "overseas": {"ADJ": 1}, "Especially": {"ADV": 1}, "Germany": {"NOUN": 1}, "d": {"ADV": 1, "NOUN": 1}, "thankful": {"ADJ": 1}, "turn": {"VERB": 3}, "descriptions": {"NOUN": 1}, "Please": {"VERB": 1, "NOUN": 1}, "HAVE": {"VERB": 1}, "THE": {"DET": 1}, "SAME": {"NOUN": 1}, "ISSUE": {"NOUN": 1}, "OFF": {"NOUN": 1}, "insane": {"NOUN": 1}, "x\\_x": {"NOUN": 1}, "i": {"NOUN": 3, "ADJ": 1}, "fixed": {"VERB": 2}, "also": {"ADV": 2}, "24": {"NUM": 1}, "Ya": {"ADP": 1}, "15": {"NUM": 1}, "mins": {"NOUN": 1}, "which": {"DET": 1}, "normal": {"ADJ": 1}, "online": {"VERB": 1}, "should": {"VERB": 4}, "less": {"ADJ": 1}, "Yea": {"NOUN": 1}, "ive": {"ADJ": 2}, "using": {"VERB": 2}, "ad": {"NOUN": 1}, "block": {"NOUN": 1}, "screwed": {"VERB": 1}, "browser": {"NOUN": 1}, "watching": {"VERB": 2}, "my": {"PRON": 8}, "phone": {"NOUN": 1}, "worst": {"ADJ": 1}, "pretty": {"ADJ": 1, "ADV": 1}, "terrible": {"ADJ": 1}, "bare": {"VERB": 1}, "got": {"VERB": 2}, "email": {"NOUN": 1}, "saying": {"VERB": 2}, "serious": {"ADJ": 1}, "Perfect": {"ADJ": 1}, "timing": {"NOUN": 1}, "eat": {"VERB": 1}, "burgers": {"NOUN": 1}, "new": {"ADJ": 3}, "laptop": {"NOUN": 1}, "try": {"VERB": 1}, "bringing": {"VERB": 1}, "S07E02": {"NOUN": 1}, "Know": {"VERB": 1}, "Your": {"PRON": 1}, "Onions": {"NOUN": 1}, "pete": {"ADJ": 1}, "Nowalk": {"NOUN": 1}, "died": {"VERB": 1}, "coronavirus": {"NOUN": 1}, "murder": {"NOUN": 1}, "S07E01": {"NOUN": 1}, "Deal": {"NOUN": 2}, "Thought": {"VERB": 1}, "Poor": {"NOUN": 1}, "Katherine": {"NOUN": 1}, "Petition": {"NOUN": 1}, "Schooled": {"NOUN": 1}, "Did": {"NOUN": 2}, "logo": {"ADJ": 1, "NOUN": 1}, "change": {"NOUN": 1}, "recently": {"ADV": 1}, "local": {"ADJ": 3}, "changed": {"VERB": 2}, "easy": {"ADJ": 1}, "Abc": {"NOUN": 1}, "This": {"DET": 4}, "letter": {"NOUN": 1}, "Maybe": {"ADV": 1}, "lowest": {"ADJ": 1}, "effort": {"NOUN": 1}, "post": {"NOUN": 1}, "'ve": {"VERB": 2}, "ever": {"ADV": 1}, "seen": {"VERB": 1}, "ready": {"ADJ": 1}, "hype": {"NOUN": 1}, "sequel": {"NOUN": 1}, "life": {"NOUN": 1}, "Thank": {"NOUN": 1}, "Im": {"NOUN": 2}, "read": {"NOUN": 1}, "B": {"NOUN": 1}, "C": {"NOUN": 1}, "stop": {"VERB": 1}, "showing": {"VERB": 1, "NOUN": 1}, "annual": {"ADJ": 1}, "Ten": {"NOUN": 1}, "Commandment": {"NOUN": 1}, "movie": {"NOUN": 1}, "Saturday": {"NOUN": 1}, "night": {"NOUN": 1}, "did": {"VERB": 3}, "air": {"NOUN": 2}, "Televised": {"VERB": 1}, "skipped": {"VERB": 1}, "passed": {"VERB": 1}, "BluRay": {"NOUN": 2}, "copy": {"NOUN": 1}, "worth": {"ADP": 1}, "cinematic": {"ADJ": 1}, "home": {"NOUN": 1}, "experience": {"NOUN": 1}, "today": {"NOUN": 1}, "needs": {"VERB": 1}, "rely": {"VERB": 1}, "broadcast": {"ADJ": 1, "NOUN": 2}, "version": {"NOUN": 1}, "epic": {"NOUN": 1}, "film": {"NOUN": 2}, "literally": {"ADV": 1}, "person": {"NOUN": 1}, "own": {"VERB": 2}, "vhs": {"NOUN": 1}, "DVD": {"NOUN": 1}, "take": {"VERB": 1}, "your": {"PRON": 3}, "pick": {"NOUN": 1}, "makes": {"VERB": 1}, "perfect": {"ADJ": 1}, "Easter": {"NOUN": 2}, "gift": {"NOUN": 1}, "Christmas": {"NOUN": 1}, "stocking": {"VERB": 1}, "stuffer": {"NOUN": 1}, "breaks": {"NOUN": 1}, "period": {"NOUN": 1}, "//tveveryday.com/the-ten-commandments-april-4-2020-442020-4-april-saturday-abc/": {"ADJ": 1, "NOUN": 1}, "Dang": {"NOUN": 1}, "eve": {"VERB": 1}, "Oh": {"X": 1}, "wow": {"NOUN": 1}, "early": {"ADJ": 1}, "farted": {"VERB": 1}, "smelled": {"VERB": 1}, "fart": {"NOUN": 1}, "messed": {"VERB": 1}, "special": {"ADJ": 1}, "covering": {"VERB": 1}, "Coronavirus": {"NOUN": 1}, "tonight": {"NOUN": 1}, "host": {"NOUN": 1}, "incorrectly": {"ADV": 1}, "stated": {"VERB": 1}, "fever": {"NOUN": 1}, "104": {"NUM": 1}, "degrees": {"NOUN": 2}, "100.4": {"NUM": 1}, "sling": {"VERB": 1}, "prime": {"ADJ": 1}, "Netflix": {"NOUN": 1}, "ROKU": {"NOUN": 1}, "How": {"NOUN": 1}, "log": {"NOUN": 1}, "into": {"ADP": 1}, "GO": {"NOUN": 1}, "cable": {"NOUN": 1}, "provider": {"NOUN": 2}, "remote": {"ADJ": 2}, "antenna": {"NOUN": 2}, "Wait": {"NOUN": 1}, "area": {"NOUN": 1}, "Talkeetna": {"NOUN": 1}, "Alaska": {"NOUN": 1}, "far": {"ADV": 1}, "need": {"VERB": 2}, "Roku": {"NOUN": 1}, "Only": {"ADV": 1}, "available": {"ADJ": 1}, "powered": {"VERB": 1}, "worked": {"VERB": 1}, "fine": {"ADJ": 2}, "place": {"NOUN": 1}, "ended": {"VERB": 1}, "Hulu": {"NOUN": 2}, "plus": {"CONJ": 1}, "im": {"VERB": 1}, "disabled": {"ADJ": 1}, "fan": {"NOUN": 1}, "tweeted": {"VERB": 1}, "hayley": {"VERB": 1}, "mirror": {"NOUN": 1}, "account": {"NOUN": 1}, "error": {"NOUN": 1}, "message": {"NOUN": 1}, "newest": {"ADJ": 1}, "Stumptown": {"NOUN": 1}, "however": {"ADV": 1}, "able": {"ADJ": 1}, "Casting": {"VERB": 1}, "chrome": {"ADJ": 1}, "plz": {"NOUN": 1}, "ty": {"VERB": 1}, "Way": {"NOUN": 1}, "LEGALLY": {"NOUN": 1}, "Buy": {"NOUN": 1}, "Stream": {"NOUN": 1}, "Oscars": {"NOUN": 3}, "abc.com": {"ADJ": 1}, "//abc.com/": {"NOUN": 1}, "stream": {"NOUN": 1}, "require": {"VERB": 1}, "Comcast": {"NOUN": 1}, "spend": {"VERB": 1}, "$": {".": 1}, "500+": {"NUM": 1}, "per": {"ADP": 2}, "directly": {"ADV": 1}, "license": {"VERB": 1}, "options": {"NOUN": 1}, "pay": {"NOUN": 1}, "view": {"NOUN": 2}, "b": {"NOUN": 2}, "c": {"NOUN": 1}, "e": {"NOUN": 1}, "f": {"NOUN": 1}, "g": {"NOUN": 1}, "h": {"NOUN": 1}, "j": {"NOUN": 1}, "k": {"VERB": 1}, "l-m-n-o-p.": {"ADJ": 1}, "q": {"NOUN": 1}, "r": {"NOUN": 1}, "u": {"ADJ": 1}, "v": {"NOUN": 1}, "w": {"NOUN": 1}, "x": {"NOUN": 1}, "y": {"NOUN": 1}, "z": {"NOUN": 1}, "Now": {"ADV": 1}, "cs": {"NOUN": 1}, "next": {"ADJ": 2}, "won": {"VERB": 1}, "sing": {"VERB": 1}, "S06E12-13": {"ADJ": 1}, "Sign": {"NOUN": 1}, "Life": {"NOUN": 1}, "S06E11": {"NOUN": 1}, "From": {"ADP": 1, "NOUN": 1}, "Ashes": {"NOUN": 1}, "S06E10": {"NOUN": 1}, "Leap": {"NOUN": 1}, "S06E09": {"NOUN": 1}, "Collision": {"NOUN": 2}, "Course": {"NOUN": 2}, "Part": {"NOUN": 2}, "II": {"NOUN": 1}, "S06E08": {"NOUN": 1}, "S06E07": {"NOUN": 1}, "Toldja": {"NOUN": 1}, "S06E06": {"NOUN": 1}, "Inescapable": {"ADJ": 1}, "S06E05": {"NOUN": 1}, "Other": {"ADJ": 1}, "Thing": {"NOUN": 1}, "S06E04": {"NOUN": 1}, "Code": {"NOUN": 1}, "Yellow": {"NOUN": 1}, "S06E03": {"NOUN": 1}, "Fear": {"NOUN": 1}, "Loathing": {"VERB": 1}, "Planet": {"NOUN": 1}, "Kitson": {"NOUN": 1}, "S06E02": {"NOUN": 1}, "Window": {"NOUN": 1}, "Opportunity": {"NOUN": 1}, "S06E01": {"NOUN": 1}, "Missing": {"VERB": 1}, "Pieces": {"NOUN": 1}, "'Iron": {"NUM": 1}, "Fist": {"NOUN": 1}, "Showrunner": {"NOUN": 1}, "Signs": {"NOUN": 1}, "Overall": {"NOUN": 1}, "Studios": {"NOUN": 1}, "Just": {"ADV": 1}, "clear": {"ADJ": 1}, "referring": {"VERB": 1}, "*": {"NOUN": 2}, "2": {"NUM": 2}, "showrunner": {"NOUN": 1}, "Raven": {"NOUN": 1}, "Metzner": {"NOUN": 1}, "Fix": {"NOUN": 2}, "1x06": {"NUM": 1}, "Fugitive": {"NOUN": 1}, "1x05": {"NUM": 1}, "Lie": {"NOUN": 1}, "Me": {"NOUN": 1}, "Trebek": {"NOUN": 1}, "encourages": {"VERB": 1}, "amid": {"ADP": 1}, "cancer": {"NOUN": 1}, "'Keep": {"VERB": 1}, "faith": {"NOUN": 1}, "sad": {"ADJ": 2}, "Show": {"NOUN": 1}, "Million": {"NOUN": 2}, "Little": {"NOUN": 2}, "Things": {"NOUN": 2}, "Found": {"NOUN": 1}, "playlist": {"NOUN": 1}, "//open.spotify.com/playlist/7xVrPVsC9ZTD9NhrWzEgp6": {"NOUN": 2}, "Has": {"VERB": 1}, "checked": {"VERB": 1}, "Matters": {"NOUN": 1}, "Steve": {"NOUN": 1}, "Urkel": {"NOUN": 1}, "Channing": {"VERB": 1}, "Dungey": {"NOUN": 1}, "Exits": {"NOUN": 1}, "Chief": {"NOUN": 1}, "Karey": {"NOUN": 1}, "Burke": {"NOUN": 1}, "Replace": {"VERB": 1}, "Her": {"PRON": 1}, "Orders": {"NOUN": 1}, "Additional": {"NOUN": 1}, "Scripts": {"NOUN": 1}, "Four": {"NOUN": 1}, "Shows": {"NOUN": 1}, "Including": {"NOUN": 1}, "Rookie": {"NOUN": 1}, "Episode": {"NOUN": 1}, "Canadian": {"NOUN": 1}, "Airing": {"NOUN": 1}, "S15E01/S15E02": {"NOUN": 1}, "With": {"ADP": 1}, "Wild": {"NOUN": 1}, "Desire": {"NOUN": 1}, ";": {".": 1}, "Broken": {"NOUN": 1}, "Together": {"NOUN": 1}, "TGIF": {"NOUN": 1}, "Robert": {"NOUN": 1}, "Englund": {"NOUN": 1}, "return": {"NOUN": 1}, "Freddy": {"NOUN": 1}, "Krueger": {"NOUN": 1}, "happen": {"VERB": 3}, "publicly": {"ADV": 1}, "owned": {"VERB": 3}, "instead": {"ADV": 3}, "being": {"VERB": 3}, "privately": {"ADV": 1}, "Those": {"DET": 1}, "hypothetical": {"ADJ": 1}, "looks": {"VERB": 1}, "ambiguously": {"ADV": 1}, "national": {"ADJ": 1}, "public": {"ADJ": 2}, "broadcaster": {"NOUN": 2}, "US": {"NOUN": 1}, "PBS": {"NOUN": 1}, "That": {"DET": 2}, "becauae": {"ADJ": 1}, "22": {"NUM": 1}, "airs": {"VERB": 3}, "commericals": {"NOUN": 1}, "X": {"NOUN": 1}, "proud": {"ADJ": 1}, "sponsor": {"NOUN": 1}, "due": {"ADJ": 1}, "lots": {"NOUN": 1}, "money": {"NOUN": 1}, "their": {"PRON": 1}, "theme": {"NOUN": 1}, "parks": {"NOUN": 1}, "movies": {"NOUN": 1}, "stuff": {"NOUN": 1}, "XD": {"NOUN": 1}, "Here": {"ADV": 1}, "question": {"NOUN": 1}, "USA": {"NOUN": 1}, "Canada": {"NOUN": 1}, "CBC": {"NOUN": 1}, "UK": {"NOUN": 1}, "BBC": {"NOUN": 1}, "Australia": {"NOUN": 1}, "Japan": {"NOUN": 1}, "NHK": {"NOUN": 1}, "owning": {"VERB": 2}, "government-owned": {"ADJ": 1}, "'Roseanne": {"PRT": 2}, "spinoff": {"NOUN": 2}, "'The": {"PRT": 2}, "Conners": {"NOUN": 1}, "premiere": {"VERB": 1}, "fall": {"NOUN": 1}, "Crossing": {"NOUN": 1}, "Canceled": {"VERB": 2}, "One": {"NUM": 1}, "Bring": {"NOUN": 1}, "nooo": {"NOUN": 1}, "wasted": {"VERB": 1}, "SO": {"ADV": 1}, "Was": {"NOUN": 1}, "devastated": {"VERB": 1}, "learn": {"VERB": 1}, "canceled": {"VERB": 2}, "brought": {"VERB": 1}, "great": {"ADJ": 1}, "well": {"ADV": 1}, "grounded": {"VERB": 1}, "enough": {"ADV": 1}, "reach": {"VERB": 1}, "wide": {"ADJ": 1}, "audience": {"NOUN": 1}, "SyFy": {"NOUN": 1}, "types": {"NOUN": 1}, "Really": {"NOUN": 1}, "those": {"DET": 1}, "miraculous": {"ADJ": 1}, "reentry": {"NOUN": 1}, "Roseanne": {"NOUN": 3}, "pitch": {"NOUN": 1}, "meeting": {"NOUN": 1}, "producers": {"NOUN": 1}, "await": {"VERB": 1}, "decision": {"NOUN": 1}, "Gilbert": {"NOUN": 1}, "Barr": {"NOUN": 2}, "Imus": {"NOUN": 1}, "Jimmy": {"NOUN": 1}, "Greek": {"NOUN": 1}, "Middle": {"NOUN": 1}, "Spinoff": {"NOUN": 1}, "Starring": {"NOUN": 1}, "Eden": {"NOUN": 1}, "Sher": {"NOUN": 1}, "Eyed": {"NOUN": 1}, "At": {"ADP": 1}, "Original": {"NOUN": 1}, "Creators": {"NOUN": 1}, "steep": {"ADJ": 1}, "consequences": {"NOUN": 2}, "bet": {"ADV": 1}, "cancels": {"NOUN": 1}, "Rosanne": {"NOUN": 1}, "revival": {"NOUN": 1}, "comedian": {"ADJ": 1}, "racist": {"NOUN": 1}, "tweets": {"NOUN": 1}, "She": {"PRON": 1}, "walked": {"VERB": 1}, "million": {"NUM": 1}, "dollar": {"NOUN": 1}, "deal": {"NOUN": 1}, "over": {"ADP": 1}, "tweet": {"NOUN": 2}, "..": {"NOUN": 1}, "Boycotting": {"NOUN": 1}, "kind": {"NOUN": 1}, "Trump": {"NOUN": 2}, "nothing": {"NOUN": 1}, "Lets": {"NOUN": 1}, "Put": {"VERB": 1}, "Political": {"NOUN": 1, "ADJ": 1}, "Bias": {"NOUN": 1}, "Following": {"VERB": 1}, "Racist": {"NOUN": 1}, "Tweet": {"NOUN": 1}, "boycotting": {"VERB": 1}, "Free": {"ADJ": 1, "NOUN": 1}, "speech": {"NOUN": 4}, "our": {"PRON": 1}, "amendment": {"NOUN": 2}, "nasty": {"ADJ": 1}, "anything": {"NOUN": 1}, "end": {"VERB": 1}, "bias": {"NOUN": 1}, "Join": {"VERB": 1}, "Boycott": {"NOUN": 1}, "God": {"NOUN": 1}, "joke": {"NOUN": 1}, "Right": {"NOUN": 1}, "Speech": {"NOUN": 1}, "means": {"VERB": 1}, "government": {"NOUN": 1}, "arrest": {"VERB": 1}, "protect": {"VERB": 1}, "//xkcd.com/1357/": {"NOUN": 1}, "talking": {"VERB": 2}, "free": {"ADJ": 1}, "conservative": {"ADJ": 1}, "points": {"NOUN": 1}, "taken": {"VERB": 1}, "hate": {"ADJ": 1}, "crimes": {"NOUN": 1}, "liberal": {"ADJ": 1}, "viewpoints": {"NOUN": 1}, "aren": {"VERB": 1}, "looked": {"VERB": 1}, "twice": {"ADV": 1}, "hypocracy": {"NOUN": 1}, "effectively": {"ADV": 1}, "calling": {"VERB": 2}, "muslim": {"ADJ": 1}, "ape": {"NOUN": 1}, "ass": {"NOUN": 1}, "making": {"VERB": 1}, "fun": {"NOUN": 1}, "excusing": {"VERB": 1}, "bigotry": {"NOUN": 1}, "Cancels": {"NOUN": 1}, "Chew": {"NOUN": 1}, "Expands": {"NOUN": 1}, "'GMA": {"PRT": 1}, "Third": {"NOUN": 1}, "Hour": {"NOUN": 1}, "S05E22": {"NOUN": 1}, "Designated": {"VERB": 1}, "Survivor": {"NOUN": 1}, "S02E22": {"NOUN": 1}, "Run": {"NOUN": 1}, "RedPill": {"NOUN": 1}, "Um": {"NOUN": 1}, "pardon": {"NOUN": 1}, "dumb": {"ADJ": 1}, "S05E21": {"NOUN": 1}, "Force": {"NOUN": 1}, "Gravity": {"NOUN": 1}}